README.md
setup.cfg
setup.py
aws_test_dump/__init__.py
aws_test_dump/aws_test_dump.py
aws_test_dump.egg-info/PKG-INFO
aws_test_dump.egg-info/SOURCES.txt
aws_test_dump.egg-info/dependency_links.txt
aws_test_dump.egg-info/not-zip-safe
aws_test_dump.egg-info/requires.txt
aws_test_dump.egg-info/top_level.txt
bin/aws_test_dump
tests/__init__.py
tests/conftest.py
tests/data_dump_definition.py
tests/test_aws_test_dump.py