Metadata-Version: 1.1
Name: aws-test-dump
Version: 0.2.0
Summary: simple script for dumping and restoring aws test data for local testing
Home-page: https://github.com/DanHanson82/python-aws-test-dump
Author: Daniel Hanson
Author-email: daniel.hanson82@gmail.com
License: MIT
Platform: UNKNOWN
Classifier: Programming Language :: Python :: 2.7
